MANIFEST.in
README.md
requirements.txt
setup.cfg
setup.py
baseline_agents/__init__.py
baseline_agents/coder_agent.py
baseline_agents/coder_utils.py
baseline_agents/react_agent.py
baseline_agents/react_utils.py
baseline_agents/self_refine_agent.py
benchmark_scripts/__init__.py
benchmark_scripts/run_discovery_bench.py
benchmark_scripts/run_discovery_bench_baseline.py
benchmark_scripts/run_targetval_baseline.py
benchmark_scripts/run_targetval_benchmark.py
popper/__init__.py
popper/agent.py
popper/benchmark.py
popper/popper.py
popper/prompt_utils.py
popper/react_agent.py
popper/react_utils.py
popper/utils.py
popper/version.py
popper/llm/__init__.py
popper/llm/custom_model.py
popper/llm/prompt_utils.py
popper/llm/utils.py
popper_agent.egg-info/PKG-INFO
popper_agent.egg-info/SOURCES.txt
popper_agent.egg-info/dependency_links.txt
popper_agent.egg-info/not-zip-safe
popper_agent.egg-info/requires.txt
popper_agent.egg-info/top_level.txt