Metadata-Version: 2.1
Name: popper-agent
Version: 0.0.5
Summary: POPPER
Home-page: https://github.com/snap-stanford/POPPER
Author: POPPER Team
Author-email: kexinh@cs.stanford.edu
License: MIT
Platform: UNKNOWN
